verilog/2025-09-09/sintesi_rc.v
module MATCH_SEQ (
    buffer,
    match, match_type
);

    input [3:0] buffer;
    output match;
    output [1:0] match_type;

    wire is_type_1;
    assign #1 is_type_1 = ~buffer[0] & buffer[1] & buffer[2] & ~buffer[3];

    wire is_type_2;
    assign #1 is_type_2 = ~buffer[0] & ~buffer[1] & buffer[2] & buffer[3];

    wire is_type_3;
    assign #1 is_type_3 = buffer[0] & ~buffer[1] & buffer[2] & ~buffer[3];

    assign #1 match = is_type_1 | is_type_2 | is_type_3;
    assign #1 match_type =
                        is_type_1? 1 :
                        is_type_2 ? 2 :
                        is_type_3 ? 3 :
                                    0;
endmodule

verilog/2025-09-09/desc_rs.v
module ABC (
    x,y, eoc_x, soc_x, eoc_y , soc_y,
    dav_, rfd, t,
    clock, reset_
);

    input reset_, clock;
    input x,y;
    input eoc_x, eoc_y;
    output soc_x, soc_y;
    input rfd;
    output dav_;
    output [1:0] t;


    reg [2:0] STAR;
    reg DAV_, SOC;
    reg [1:0] T;
    
    assign soc_x = SOC;
    assign soc_y = SOC;
    assign dav_ = DAV_;
    assign t = T;

    reg [3:0] BUFFER;

    wire match;
    wire [1:0] match_type;

    localparam
        S0 = 0,
        S1 = 1,
        S2 = 2,
        S3 = 3,
        S4 = 4,
        S5 = 5;

    MATCH_SEQ rc (
        .buffer(BUFFER), .match(match), .match_type(match_type)
    );


    always @ (reset_ == 0) #1 begin
        BUFFER = 0;
        SOC = 0;
        DAV_ = 1;
        STAR = S0;
    end

    always @(posedge clock) if (reset_ == 1) #3
        casex(STAR)
            S0:
                begin
                    SOC <= 1;
                    STAR <= (eoc_x == 0 & eoc_y == 0) ? S1 : S0;
                end
            S1:
                begin
                    SOC <= 0;
                    STAR <= (eoc_x == 1 & eoc_y == 1) ? S2 : S1;
                end
            S2:
                begin
                    BUFFER <= {BUFFER[3:0], x ^ y};
                    STAR <= S3;
                end
            S3:
                begin
                    T <= match_type;
                    STAR <= (match) ? S4 : S0;
                end
            S4:
                begin
                    DAV_ <= 0;
                    STAR <=  (rfd == 0) ? S5 : S4;
                end

            S5:
                begin
                    DAV_ <= 1;
                    STAR <= (rfd == 1) ? S0 : S5;
                end
        endcase
    endmodule

verilog/2025-09-09/testbench.v
module testbench();

    wire clock;

    clock_generator clk(
        .clock(clock)
    );

    reg reset_;

    wire soc_x, soc_y;
    reg eoc_x, eoc_y;
    reg x, y;

    wire dav_;
    reg rfd;
    wire [1:0] t;
    
    ABC dut (
        .soc_x(soc_x), .soc_y(soc_y), .eoc_x(eoc_x), .x(x), .eoc_y(eoc_y), .y(y),
        .dav_(dav_), .rfd(rfd), .t(t), 
        .clock(clock), .reset_(reset_)
    );

    // linea di errore, utile per il debug
    reg error;
    initial error = 0;
    always @(posedge error) #1
        error = 0;

    initial
        begin
            $dumpfile("waveform.vcd");
            $dumpvars;

            //the following structure is used to wait for expected signals, and fail if too much time passes
            fork : f
                begin
                    #100000;
                    $display("Timeout - waiting for signal failed");
                    disable f;
                end
            //actual tests start here
                begin
                    eoc_x = 1; eoc_y = 1;
                    rfd = 1;

                    //reset phase
                    reset_ = 0; #(clk.HALF_PERIOD);
                    
                    //first posedge
                    reset_ = 1;

                    if(soc_x !== 0)
                        $display("soc_x is not 0 after reset");

                    if(soc_y !== 0)
                        $display("soc_y is not 0 after reset");

                    if(dav_ !== 1)
                        $display("dav_ is not 1 after reset");

                    fork
                        //Produttore X
                        begin : producer_x
                            reg [4:0] i;
                            reg t_x, t_y;

                            for (i = 0; i < 16; i++) begin
                                {t_x, t_y} = get_input_sequence(i[4:0]);
                                
                                @(posedge soc_x);
                                #(1*2*clk.HALF_PERIOD); 
                                eoc_x <= 0;
                                @(negedge soc_x);
                                #(1*2*clk.HALF_PERIOD); 
                                x <= t_x;
                                #(1*2*clk.HALF_PERIOD); 
                                eoc_x <= 1;    
                            end
                        end

                        //Produttore Y
                        begin : producer_y
                            reg [4:0] i;
                            reg t_x, t_y;

                            for (i = 0; i < 16; i++) begin
                                {t_x, t_y} = get_input_sequence(i[4:0]);
                                
                                @(posedge soc_y);
                                #(2*2*clk.HALF_PERIOD); 
                                eoc_y <= 0;
                                @(negedge soc_y);
                                #(2*2*clk.HALF_PERIOD); 
                                y <= t_y;
                                #(2*2*clk.HALF_PERIOD); 
                                eoc_y <= 1;      
                            end
                        end

                        //Consumer
                        begin : consumer
                            reg [2:0] i;
                            reg [1:0] t_T;

                            for (i = 0; i < 6; i++) begin
                                t_T = get_types_sequence(i[2:0]);

                                @(negedge dav_);
                                if(t !== t_T) begin
                                    $display("Test #%g failed, expected %g, got %g", i, t_T, t);
                                    error = 1;
                                end
                                #(2*clk.HALF_PERIOD); rfd <= 0;
                                @(posedge dav_);
                                #(2*clk.HALF_PERIOD); rfd <= 1;
                            end
                        end
                    join

                    disable f;
                end
            join

            $finish;
        end

    function automatic [6:0] get_input_sequence;
        input [4:0] i;
        reg x, y;
        
        begin
            case(i[3:0])
                0: begin
                    x = 0; y = 0; // 0
                end
                1: begin
                    x = 1; y = 0; // 1
                end
                2: begin
                    x = 0; y = 1; // 1
                end
                3: begin
                    x = 1; y = 1; // 0 -> T_1
                end
                4: begin
                    x = 1; y = 0; // 1
                end
                5: begin
                    x = 0; y = 0; // 0  
                end
                6: begin
                    x = 0; y = 1; // 1 -> T_3
                end
                7: begin
                    x = 1; y = 0; // 1
                end
                8: begin
                    x = 1; y = 1; // 0 -> T_1
                end
                9: begin
                    x = 0; y = 0; // 0 -> T_2
                end
                10: begin
                    x = 1; y = 0; // 1
                end
                11: begin
                    x = 1; y = 1; // 0
                end
                12: begin
                    x = 0; y = 1; // 1 -> T_3
                end
                13: begin
                    x = 0; y = 1; // 1
                end
                14: begin
                    x = 1; y = 1; // 0 -> T_1
                end
                15: begin
                    x = 1; y = 0; // 1
                end
            endcase

            get_input_sequence = {x, y};
        end
    endfunction

    function automatic [4:0] get_types_sequence;
        input [2:0] i;

        reg [1:0] t;

        begin
            case(i[2:0])
                0: begin
                    t = 1;
                end
                1: begin
                    t = 3;
                end
                2: begin
                    t = 1;
                end
                3: begin
                    t = 2;
                end
                4: begin
                    t = 3;
                end
                5: begin
                    t = 1;
                end
                default: begin
                    t = 0;
                end
            endcase

            get_types_sequence = t;
        end
    endfunction
endmodule

// generatore del segnale di clock
module clock_generator(
    clock
);
    output clock;

    parameter HALF_PERIOD = 5;

    reg CLOCK;
    assign clock = CLOCK;

    initial CLOCK <= 0;
    always #HALF_PERIOD CLOCK <= ~CLOCK;

endmodule

verilog/2025-09-09/waveform_desc.vcd
$date
	Fri Dec  5 16:56:48 2025
$end
$version
	Icarus Verilog
$end
$timescale
	1s
$end
$scope module testbench $end
$var wire 2 ! t [1:0] $end
$var wire 1 " soc_y $end
$var wire 1 # soc_x $end
$var wire 1 $ dav_ $end
$var wire 1 % clock $end
$var reg 1 & eoc_x $end
$var reg 1 ' eoc_y $end
$var reg 1 ( error $end
$var reg 1 ) reset_ $end
$var reg 1 * rfd $end
$var reg 1 + x $end
$var reg 1 , y $end
$scope function get_input_sequence $end
$upscope $end
$scope function get_types_sequence $end
$upscope $end
$scope module clk $end
$var wire 1 % clock $end
$var parameter 32 - HALF_PERIOD $end
$var reg 1 . CLOCK $end
$upscope $end
$scope module dut $end
$var wire 1 % clock $end
$var wire 1 $ dav_ $end
$var wire 1 & eoc_x $end
$var wire 1 ' eoc_y $end
$var wire 1 ) reset_ $end
$var wire 1 * rfd $end
$var wire 1 # soc_x $end
$var wire 1 " soc_y $end
$var wire 2 / t [1:0] $end
$var wire 1 + x $end
$var wire 1 , y $end
$var wire 2 0 match_type [1:0] $end
$var wire 1 1 match $end
$var parameter 32 2 S0 $end
$var parameter 32 3 S1 $end
$var parameter 32 4 S2 $end
$var parameter 32 5 S3 $end
$var parameter 32 6 S4 $end
$var parameter 32 7 S5 $end
$var reg 4 8 BUFFER [3:0] $end
$var reg 1 9 DAV_ $end
$var reg 1 : SOC $end
$var reg 3 ; STAR [2:0] $end
$var reg 2 < T [1:0] $end
$scope module rc $end
$var wire 4 = buffer [3:0] $end
$var wire 1 > is_type_1 $end
$var wire 1 ? is_type_2 $end
$var wire 1 @ is_type_3 $end
$var wire 1 1 match $end
$var wire 2 A match_type [1:0] $end
$upscope $end
$upscope $end
$scope fork f $end
$scope begin consumer $end
$var reg 3 B i [2:0] $end
$var reg 2 C t_T [1:0] $end
$upscope $end
$scope begin producer_x $end
$var reg 5 D i [4:0] $end
$var reg 1 E t_x $end
$var reg 1 F t_y $end
$upscope $end
$scope begin producer_y $end
$var reg 5 G i [4:0] $end
$var reg 1 H t_x $end
$var reg 1 I t_y $end
$upscope $end
$upscope $end
$upscope $end
$enddefinitions $end
$comment Show the parameter values. $end
$dumpall
b101 7
b100 6
b11 5
b10 4
b1 3
b0 2
b101 -
$end
#0
$dumpvars
xI
xH
bx G
xF
xE
bx D
bx C
bx B
bx A
x@
x?
x>
bx =
bx <
bx ;
x:
x9
bx 8
x1
bx 0
bx /
0.
x,
x+
1*
0)
0(
1'
1&
0%
x$
x#
x"
bx !
$end
#1
b0 ;
1$
19
0"
0#
0:
b0 8
b0 =
#2
0>
0@
0?
#3
b0 0
b0 A
01
#5
1%
1.
0E
0F
b0 D
0H
0I
b0 G
b1 C
b0 B
1)
#8
1"
1#
1:
#10
0%
0.
#15
1%
1.
#18
0&
#20
0%
0.
#25
1%
1.
#28
0'
#30
0%
0.
#35
1%
1.
#38
b1 ;
#40
0%
0.
#45
1%
1.
#48
0"
0#
0:
#50
0%
0.
#55
1%
1.
#58
0+
#60
0%
0.
#65
1%
1.
#68
1&
0,
1E
b1 D
#70
0%
0.
#75
1%
1.
#80
0%
0.
#85
1%
1.
#88
1'
1H
b1 G
#90
0%
0.
#95
1%
1.
#98
b10 ;
#100
0%
0.
#105
1%
1.
#108
b11 ;
#110
0%
0.
#115
1%
1.
#118
b0 ;
b0 !
b0 /
b0 <
#120
0%
0.
#125
1%
1.
#128
1"
1#
1:
#130
0%
0.
#135
1%
1.
#138
0&
#140
0%
0.
#145
1%
1.
#148
0'
#150
0%
0.
#155
1%
1.
#158
b1 ;
#160
0%
0.
#165
1%
1.
#168
0"
0#
0:
#170
0%
0.
#175
1%
1.
#178
1+
#180
0%
0.
#185
1%
1.
#188
1&
0E
1F
b10 D
#190
0%
0.
#195
1%
1.
#200
0%
0.
#205
1%
1.
#208
1'
0H
1I
b10 G
#210
0%
0.
#215
1%
1.
#218
b10 ;
#220
0%
0.
#225
1%
1.
#228
b11 ;
b1 8
b1 =
#230
0%
0.
#235
1%
1.
#238
b0 ;
#240
0%
0.
#245
1%
1.
#248
1"
1#
1:
#250
0%
0.
#255
1%
1.
#258
0&
#260
0%
0.
#265
1%
1.
#268
0'
#270
0%
0.
#275
1%
1.
#278
b1 ;
#280
0%
0.
#285
1%
1.
#288
0"
0#
0:
#290
0%
0.
#295
1%
1.
#298
0+
#300
0%
0.
#305
1%
1.
#308
1&
1,
1E
b11 D
#310
0%
0.
#315
1%
1.
#320
0%
0.
#325
1%
1.
#328
1'
1H
b11 G
#330
0%
0.
#335
1%
1.
#338
b10 ;
#340
0%
0.
#345
1%
1.
#348
b11 ;
b11 8
b11 =
#350
0%
0.
#355
1%
1.
#358
b0 ;
#360
0%
0.
#365
1%
1.
#368
1"
1#
1:
#370
0%
0.
#375
1%
1.
#378
0&
#380
0%
0.
#385
1%
1.
#388
0'
#390
0%
0.
#395
1%
1.
#398
b1 ;
#400
0%
0.
#405
1%
1.
#408
0"
0#
0:
#410
0%
0.
#415
1%
1.
#418
1+
#420
0%
0.
#425
1%
1.
#428
1&
0F
b100 D
#430
0%
0.
#435
1%
1.
#440
0%
0.
#445
1%
1.
#448
1'
0I
b100 G
#450
0%
0.
#455
1%
1.
#458
b10 ;
#460
0%
0.
#465
1%
1.
#468
b11 ;
b110 8
b110 =
#469
1>
#470
0%
0.
11
b1 0
b1 A
#475
1%
1.
#478
b100 ;
b1 !
b1 /
b1 <
#480
0%
0.
#485
1%
1.
#488
0$
09
#490
0%
0.
#495
1%
1.
#498
0*
#500
0%
0.
#505
1%
1.
#508
b101 ;
#510
0%
0.
#515
1%
1.
#518
1$
19
#520
0%
0.
#525
1%
1.
#528
1*
b11 C
b1 B
#530
0%
0.
#535
1%
1.
#538
b0 ;
#540
0%
0.
#545
1%
1.
#548
1"
1#
1:
#550
0%
0.
#555
1%
1.
#558
0&
#560
0%
0.
#565
1%
1.
#568
0'
#570
0%
0.
#575
1%
1.
#578
b1 ;
#580
0%
0.
#585
1%
1.
#588
0"
0#
0:
#590
0%
0.
#595
1%
1.
#600
0%
0.
#605
1%
1.
#608
1&
0,
0E
b101 D
#610
0%
0.
#615
1%
1.
#620
0%
0.
#625
1%
1.
#628
1'
0H
b101 G
#630
0%
0.
#635
1%
1.
#638
b10 ;
#640
0%
0.
#645
1%
1.
#648
b11 ;
b1101 8
b1101 =
#649
0>
#650
0%
0.
01
b0 0
b0 A
#655
1%
1.
#658
b0 ;
b0 !
b0 /
b0 <
#660
0%
0.
#665
1%
1.
#668
1"
1#
1:
#670
0%
0.
#675
1%
1.
#678
0&
#680
0%
0.
#685
1%
1.
#688
0'
#690
0%
0.
#695
1%
1.
#698
b1 ;
#700
0%
0.
#705
1%
1.
#708
0"
0#
0:
#710
0%
0.
#715
1%
1.
#718
0+
#720
0%
0.
#725
1%
1.
#728
1&
1F
b110 D
#730
0%
0.
#735
1%
1.
#740
0%
0.
#745
1%
1.
#748
1'
1I
b110 G
#750
0%
0.
#755
1%
1.
#758
b10 ;
#760
0%
0.
#765
1%
1.
#768
b11 ;
b1010 8
b1010 =
#770
0%
0.
#775
1%
1.
#778
b0 ;
#780
0%
0.
#785
1%
1.
#788
1"
1#
1:
#790
0%
0.
#795
1%
1.
#798
0&
#800
0%
0.
#805
1%
1.
#808
0'
#810
0%
0.
#815
1%
1.
#818
b1 ;
#820
0%
0.
#825
1%
1.
#828
0"
0#
0:
#830
0%
0.
#835
1%
1.
#840
0%
0.
#845
1%
1.
#848
1&
1,
1E
0F
b111 D
#850
0%
0.
#855
1%
1.
#860
0%
0.
#865
1%
1.
#868
1'
1H
0I
b111 G
#870
0%
0.
#875
1%
1.
#878
b10 ;
#880
0%
0.
#885
1%
1.
#888
b11 ;
b101 8
b101 =
#889
1@
#890
0%
0.
b11 0
b11 A
11
#895
1%
1.
#898
b100 ;
b11 !
b11 /
b11 <
#900
0%
0.
#905
1%
1.
#908
0$
09
#910
0%
0.
#915
1%
1.
#918
0*
#920
0%
0.
#925
1%
1.
#928
b101 ;
#930
0%
0.
#935
1%
1.
#938
1$
19
#940
0%
0.
#945
1%
1.
#948
1*
b1 C
b10 B
#950
0%
0.
#955
1%
1.
#958
b0 ;
#960
0%
0.
#965
1%
1.
#968
1"
1#
1:
#970
0%
0.
#975
1%
1.
#978
0&
#980
0%
0.
#985
1%
1.
#988
0'
#990
0%
0.
#995
1%
1.
#998
b1 ;
#1000
0%
0.
#1005
1%
1.
#1008
0"
0#
0:
#1010
0%
0.
#1015
1%
1.
#1018
1+
#1020
0%
0.
#1025
1%
1.
#1028
1&
0,
1F
b1000 D
#1030
0%
0.
#1035
1%
1.
#1040
0%
0.
#1045
1%
1.
#1048
1'
1I
b1000 G
#1050
0%
0.
#1055
1%
1.
#1058
b10 ;
#1060
0%
0.
#1065
1%
1.
#1068
b11 ;
b1011 8
b1011 =
#1069
0@
#1070
0%
0.
b0 0
b0 A
01
#1075
1%
1.
#1078
b0 ;
b0 !
b0 /
b0 <
#1080
0%
0.
#1085
1%
1.
#1088
1"
1#
1:
#1090
0%
0.
#1095
1%
1.
#1098
0&
#1100
0%
0.
#1105
1%
1.
#1108
0'
#1110
0%
0.
#1115
1%
1.
#1118
b1 ;
#1120
0%
0.
#1125
1%
1.
#1128
0"
0#
0:
#1130
0%
0.
#1135
1%
1.
#1140
0%
0.
#1145
1%
1.
#1148
1&
1,
0E
0F
b1001 D
#1150
0%
0.
#1155
1%
1.
#1160
0%
0.
#1165
1%
1.
#1168
1'
0H
0I
b1001 G
#1170
0%
0.
#1175
1%
1.
#1178
b10 ;
#1180
0%
0.
#1185
1%
1.
#1188
b11 ;
b110 8
b110 =
#1189
1>
#1190
0%
0.
11
b1 0
b1 A
#1195
1%
1.
#1198
b100 ;
b1 !
b1 /
b1 <
#1200
0%
0.
#1205
1%
1.
#1208
0$
09
#1210
0%
0.
#1215
1%
1.
#1218
0*
#1220
0%
0.
#1225
1%
1.
#1228
b101 ;
#1230
0%
0.
#1235
1%
1.
#1238
1$
19
#1240
0%
0.
#1245
1%
1.
#1248
1*
b10 C
b11 B
#1250
0%
0.
#1255
1%
1.
#1258
b0 ;
#1260
0%
0.
#1265
1%
1.
#1268
1"
1#
1:
#1270
0%
0.
#1275
1%
1.
#1278
0&
#1280
0%
0.
#1285
1%
1.
#1288
0'
#1290
0%
0.
#1295
1%
1.
#1298
b1 ;
#1300
0%
0.
#1305
1%
1.
#1308
0"
0#
0:
#1310
0%
0.
#1315
1%
1.
#1318
0+
#1320
0%
0.
#1325
1%
1.
#1328
1&
0,
1E
b1010 D
#1330
0%
0.
#1335
1%
1.
#1340
0%
0.
#1345
1%
1.
#1348
1'
1H
b1010 G
#1350
0%
0.
#1355
1%
1.
#1358
b10 ;
#1360
0%
0.
#1365
1%
1.
#1368
b11 ;
b1100 8
b1100 =
#1369
1?
0>
#1370
0%
0.
b10 0
b10 A
#1375
1%
1.
#1378
b100 ;
b10 !
b10 /
b10 <
#1380
0%
0.
#1385
1%
1.
#1388
0$
09
#1390
0%
0.
#1395
1%
1.
#1398
0*
#1400
0%
0.
#1405
1%
1.
#1408
b101 ;
#1410
0%
0.
#1415
1%
1.
#1418
1$
19
#1420
0%
0.
#1425
1%
1.
#1428
1*
b11 C
b100 B
#1430
0%
0.
#1435
1%
1.
#1438
b0 ;
#1440
0%
0.
#1445
1%
1.
#1448
1"
1#
1:
#1450
0%
0.
#1455
1%
1.
#1458
0&
#1460
0%
0.
#1465
1%
1.
#1468
0'
#1470
0%
0.
#1475
1%
1.
#1478
b1 ;
#1480
0%
0.
#1485
1%
1.
#1488
0"
0#
0:
#1490
0%
0.
#1495
1%
1.
#1498
1+
#1500
0%
0.
#1505
1%
1.
#1508
1&
1F
b1011 D
#1510
0%
0.
#1515
1%
1.
#1520
0%
0.
#1525
1%
1.
#1528
1'
1I
b1011 G
#1530
0%
0.
#1535
1%
1.
#1538
b10 ;
#1540
0%
0.
#1545
1%
1.
#1548
b11 ;
b1001 8
b1001 =
#1549
0?
#1550
0%
0.
b0 0
b0 A
01
#1555
1%
1.
#1558
b0 ;
b0 !
b0 /
b0 <
#1560
0%
0.
#1565
1%
1.
#1568
1"
1#
1:
#1570
0%
0.
#1575
1%
1.
#1578
0&
#1580
0%
0.
#1585
1%
1.
#1588
0'
#1590
0%
0.
#1595
1%
1.
#1598
b1 ;
#1600
0%
0.
#1605
1%
1.
#1608
0"
0#
0:
#1610
0%
0.
#1615
1%
1.
#1620
0%
0.
#1625
1%
1.
#1628
1&
1,
0E
b1100 D
#1630
0%
0.
#1635
1%
1.
#1640
0%
0.
#1645
1%
1.
#1648
1'
0H
b1100 G
#1650
0%
0.
#1655
1%
1.
#1658
b10 ;
#1660
0%
0.
#1665
1%
1.
#1668
b11 ;
b10 8
b10 =
#1670
0%
0.
#1675
1%
1.
#1678
b0 ;
#1680
0%
0.
#1685
1%
1.
#1688
1"
1#
1:
#1690
0%
0.
#1695
1%
1.
#1698
0&
#1700
0%
0.
#1705
1%
1.
#1708
0'
#1710
0%
0.
#1715
1%
1.
#1718
b1 ;
#1720
0%
0.
#1725
1%
1.
#1728
0"
0#
0:
#1730
0%
0.
#1735
1%
1.
#1738
0+
#1740
0%
0.
#1745
1%
1.
#1748
1&
b1101 D
#1750
0%
0.
#1755
1%
1.
#1760
0%
0.
#1765
1%
1.
#1768
1'
b1101 G
#1770
0%
0.
#1775
1%
1.
#1778
b10 ;
#1780
0%
0.
#1785
1%
1.
#1788
b11 ;
b101 8
b101 =
#1789
1@
#1790
0%
0.
b11 0
b11 A
11
#1795
1%
1.
#1798
b100 ;
b11 !
b11 /
b11 <
#1800
0%
0.
#1805
1%
1.
#1808
0$
09
#1810
0%
0.
#1815
1%
1.
#1818
0*
#1820
0%
0.
#1825
1%
1.
#1828
b101 ;
#1830
0%
0.
#1835
1%
1.
#1838
1$
19
#1840
0%
0.
#1845
1%
1.
#1848
1*
b1 C
b101 B
#1850
0%
0.
#1855
1%
1.
#1858
b0 ;
#1860
0%
0.
#1865
1%
1.
#1868
1"
1#
1:
#1870
0%
0.
#1875
1%
1.
#1878
0&
#1880
0%
0.
#1885
1%
1.
#1888
0'
#1890
0%
0.
#1895
1%
1.
#1898
b1 ;
#1900
0%
0.
#1905
1%
1.
#1908
0"
0#
0:
#1910
0%
0.
#1915
1%
1.
#1920
0%
0.
#1925
1%
1.
#1928
1&
1E
b1110 D
#1930
0%
0.
#1935
1%
1.
#1940
0%
0.
#1945
1%
1.
#1948
1'
1H
b1110 G
#1950
0%
0.
#1955
1%
1.
#1958
b10 ;
#1960
0%
0.
#1965
1%
1.
#1968
b11 ;
b1011 8
b1011 =
#1969
0@
#1970
0%
0.
b0 0
b0 A
01
#1975
1%
1.
#1978
b0 ;
b0 !
b0 /
b0 <
#1980
0%
0.
#1985
1%
1.
#1988
1"
1#
1:
#1990
0%
0.
#1995
1%
1.
#1998
0&
#2000
0%
0.
#2005
1%
1.
#2008
0'
#2010
0%
0.
#2015
1%
1.
#2018
b1 ;
#2020
0%
0.
#2025
1%
1.
#2028
0"
0#
0:
#2030
0%
0.
#2035
1%
1.
#2038
1+
#2040
0%
0.
#2045
1%
1.
#2048
1&
0F
b1111 D
#2050
0%
0.
#2055
1%
1.
#2060
0%
0.
#2065
1%
1.
#2068
1'
0I
b1111 G
#2070
0%
0.
#2075
1%
1.
#2078
b10 ;
#2080
0%
0.
#2085
1%
1.
#2088
b11 ;
b110 8
b110 =
#2089
1>
#2090
0%
0.
11
b1 0
b1 A
#2095
1%
1.
#2098
b100 ;
b1 !
b1 /
b1 <
#2100
0%
0.
#2105
1%
1.
#2108
0$
09
#2110
0%
0.
#2115
1%
1.
#2118
0*
#2120
0%
0.
#2125
1%
1.
#2128
b101 ;
#2130
0%
0.
#2135
1%
1.
#2138
1$
19
#2140
0%
0.
#2145
1%
1.
#2148
1*
b110 B
#2150
0%
0.
#2155
1%
1.
#2158
b0 ;
#2160
0%
0.
#2165
1%
1.
#2168
1"
1#
1:
#2170
0%
0.
#2175
1%
1.
#2178
0&
#2180
0%
0.
#2185
1%
1.
#2188
0'
#2190
0%
0.
#2195
1%
1.
#2198
b1 ;
#2200
0%
0.
#2205
1%
1.
#2208
0"
0#
0:
#2210
0%
0.
#2215
1%
1.
#2220
0%
0.
#2225
1%
1.
#2228
1&
0,
b10000 D
#2230
0%
0.
#2235
1%
1.
#2240
0%
0.
#2245
1%
1.
#2248
1'
b10000 G
