verilog/2025-09-09/sintesi_rs.v
module ABC (
    x,y, eoc_x, soc_x, eoc_y , soc_y,
    dav_, rfd, t,
    clock, reset_
);

    input reset_, clock;
    input x,y;
    input eoc_x, eoc_y;
    output soc_x, soc_y;
    input rfd;
    output dav_;
    output [1:0] t;

    wire match;
    wire [1:0] match_type;

    wire c2,c1,c0;
    wire b5,b4,b3,b2,b1,b0;


    ABC_PO po (
        x,y,
        clock, reset_,
        b5,b4,b3,b2,b1,b0,
        c2,c1,c0,
        soc_x, soc_y,
        eoc_x, eoc_y,
        dav_, t, rfd
    );

    ABC_PC pc (
        clock, reset_,
        b5,b4,b3,b2,b1,b0,
        c2,c1,c0
    );
endmodule


module ABC_PO (
    x,y,
    clock, reset_,
    b5,b4,b3,b2,b1,b0,
    c2,c1,c0,
    soc_x, soc_y,
    eoc_x, eoc_y,
    dav_, t, rfd
);

    input reset_, clock;
    input eoc_x, eoc_y;
    input rfd;
    input x,y;
    output [1:0] t;
    output dav_;
    output soc_x, soc_y;
    input b5,b4,b3,b2,b1,b0;
    output c2,c1,c0;

    reg DAV_, SOC;
    reg [1:0] T;
    
    assign soc_x = SOC;
    assign soc_y = SOC;
    assign dav_ = DAV_;
    assign t = T;

    assign #1 c0 = eoc_x & eoc_y; // salto in s0,s1
    assign #1 c1 = match; 
    assign #1 c2 = rfd;

    reg [3:0] BUFFER;

    wire match;
    wire [1:0] match_type;


    wire c2,c1,c0;
    wire b5,b4,b3,b2,b1,b0;


  MATCH_SEQ rc (
        .buffer(BUFFER), .match(match), .match_type(match_type)
    );


    // soc
    always @ (reset_ == 0) #1 SOC <= 0;
    always @(posedge clock) if (reset_ == 1) #3
        casex({b1,b0})
            2'b00:
                begin
                    SOC <= 1;
                end
            2'b01:
                begin
                    SOC <= 0;
                end

            2'b1X:
                begin
                    SOC <= SOC;
                end
        endcase

    // buffer
    always @(reset_ == 0) #1 BUFFER <= 0;

    always @(posedge clock) if (reset_ == 1) #3
        casex(b2)
            1'b0:
                begin
                    BUFFER <= {BUFFER[3:0], x ^ y};
                end


            1'b1:
                begin
                    BUFFER <= BUFFER;
                end
        endcase

    // dav
    always @ (reset_ == 0) #1 DAV_ <= 1;

    always @(posedge clock) if (reset_ == 1) #3
        casex({b4,b3})
            2'b00:
                begin
                    DAV_ <= 0;
                end

            2'b01:
                begin
                    DAV_ <= 1;
                end

            2'b1X:
                begin
                    DAV_ <= DAV_;
                end
        endcase

    // t
    always @(posedge clock) if (reset_ == 1) #3
        casex(b5)
            1'b0:
                begin
                    T <= match_type;
                end

            1'b1:
                begin
                    T <= T;
                end
        endcase
endmodule



module ABC_PC (
    clock, reset_,
    b5,b4,b3,b2,b1,b0,
    c2,c1,c0
);

    input clock, reset_;
    output b5,b4,b3,b2,b1,b0;
    input c2,c1,c0;

    reg [2:0] STAR;
    localparam
        S0 = 0,
        S1 = 1,
        S2 = 2,
        S3 = 3,
        S4 = 4,
        S5 = 5;



    assign #1 {b5,b4,b3,b2,b1,b0} =
        (STAR == S0) ? 6'b110100 :
        (STAR == S1) ? 6'b110101 :
        (STAR == S2) ? 6'b110010 :
        (STAR == S3) ? 6'b010110 :
        (STAR == S4) ? 6'b100110 :
        (STAR == S5) ? 6'b101110 :
                       6'b000000;

    always @ (reset_ == 0) #1 begin
        STAR = S0;
    end

    always @(posedge clock) if (reset_ == 1) #3 begin
        casex(STAR)
            S0:
                begin
                    STAR <= c0 ? S0 : S1;
                end
            S1:
                begin
                    STAR <= c0 ? S2 : S1;
                end
            S2:
                begin
                    STAR <= S3;
                end
            S3:
                begin
                    STAR <= c1 ? S4 : S0;
                end
            S4:
                begin
                    STAR <=  c2 ? S4 : S5;
                end

            S5:
                begin
                    STAR <= c2 ? S0 : S5;
                end
        endcase
    end

endmodule


/*
ROM

M-addr  | b5,b4,b3,b2,b1,b0 | c_eff | M-addr T | M-addr F
-------------------------------------------------------
000     |        110100     |  00  |    000   |  001
001     |        110101     |  00  |    010   |  001
010     |        010110     |  x   |    011   |  011
011     |        100110     |  01  |    100   |  000
100     |        101110     |  10  |    100   |  101
101     |        101110     |  10  |    000  |   101
*/

verilog/2025-09-09/sintesi_rc.v
module MATCH_SEQ (
    buffer,
    match, match_type
);

    input [3:0] buffer;
    output match;
    output [1:0] match_type;

    wire is_type_1;
    assign #1 is_type_1 = ~buffer[0] & buffer[1] & buffer[2] & ~buffer[3];

    wire is_type_2;
    assign #1 is_type_2 = ~buffer[0] & ~buffer[1] & buffer[2] & buffer[3];

    wire is_type_3;
    assign #1 is_type_3 = buffer[0] & ~buffer[1] & buffer[2] & ~buffer[3];

    assign #1 match = is_type_1 | is_type_2 | is_type_3;
    assign #1 match_type =
                        is_type_1? 1 :
                        is_type_2 ? 2 :
                        is_type_3 ? 3 :
                                    0;
endmodule

verilog/2025-09-09/testbench.v
module testbench();

    wire clock;

    clock_generator clk(
        .clock(clock)
    );

    reg reset_;

    wire soc_x, soc_y;
    reg eoc_x, eoc_y;
    reg x, y;

    wire dav_;
    reg rfd;
    wire [1:0] t;
    
    ABC dut (
        .soc_x(soc_x), .soc_y(soc_y), .eoc_x(eoc_x), .x(x), .eoc_y(eoc_y), .y(y),
        .dav_(dav_), .rfd(rfd), .t(t), 
        .clock(clock), .reset_(reset_)
    );

    // linea di errore, utile per il debug
    reg error;
    initial error = 0;
    always @(posedge error) #1
        error = 0;

    initial
        begin
            $dumpfile("waveform.vcd");
            $dumpvars;

            //the following structure is used to wait for expected signals, and fail if too much time passes
            fork : f
                begin
                    #100000;
                    $display("Timeout - waiting for signal failed");
                    disable f;
                end
            //actual tests start here
                begin
                    eoc_x = 1; eoc_y = 1;
                    rfd = 1;

                    //reset phase
                    reset_ = 0; #(clk.HALF_PERIOD);
                    
                    //first posedge
                    reset_ = 1;

                    if(soc_x !== 0)
                        $display("soc_x is not 0 after reset");

                    if(soc_y !== 0)
                        $display("soc_y is not 0 after reset");

                    if(dav_ !== 1)
                        $display("dav_ is not 1 after reset");

                    fork
                        //Produttore X
                        begin : producer_x
                            reg [4:0] i;
                            reg t_x, t_y;

                            for (i = 0; i < 16; i++) begin
                                {t_x, t_y} = get_input_sequence(i[4:0]);
                                
                                @(posedge soc_x);
                                #(1*2*clk.HALF_PERIOD); 
                                eoc_x <= 0;
                                @(negedge soc_x);
                                #(1*2*clk.HALF_PERIOD); 
                                x <= t_x;
                                #(1*2*clk.HALF_PERIOD); 
                                eoc_x <= 1;    
                            end
                        end

                        //Produttore Y
                        begin : producer_y
                            reg [4:0] i;
                            reg t_x, t_y;

                            for (i = 0; i < 16; i++) begin
                                {t_x, t_y} = get_input_sequence(i[4:0]);
                                
                                @(posedge soc_y);
                                #(2*2*clk.HALF_PERIOD); 
                                eoc_y <= 0;
                                @(negedge soc_y);
                                #(2*2*clk.HALF_PERIOD); 
                                y <= t_y;
                                #(2*2*clk.HALF_PERIOD); 
                                eoc_y <= 1;      
                            end
                        end

                        //Consumer
                        begin : consumer
                            reg [2:0] i;
                            reg [1:0] t_T;

                            for (i = 0; i < 6; i++) begin
                                t_T = get_types_sequence(i[2:0]);

                                @(negedge dav_);
                                if(t !== t_T) begin
                                    $display("Test #%g failed, expected %g, got %g", i, t_T, t);
                                    error = 1;
                                end
                                #(2*clk.HALF_PERIOD); rfd <= 0;
                                @(posedge dav_);
                                #(2*clk.HALF_PERIOD); rfd <= 1;
                            end
                        end
                    join

                    disable f;
                end
            join

            $finish;
        end

    function automatic [6:0] get_input_sequence;
        input [4:0] i;
        reg x, y;
        
        begin
            case(i[3:0])
                0: begin
                    x = 0; y = 0; // 0
                end
                1: begin
                    x = 1; y = 0; // 1
                end
                2: begin
                    x = 0; y = 1; // 1
                end
                3: begin
                    x = 1; y = 1; // 0 -> T_1
                end
                4: begin
                    x = 1; y = 0; // 1
                end
                5: begin
                    x = 0; y = 0; // 0  
                end
                6: begin
                    x = 0; y = 1; // 1 -> T_3
                end
                7: begin
                    x = 1; y = 0; // 1
                end
                8: begin
                    x = 1; y = 1; // 0 -> T_1
                end
                9: begin
                    x = 0; y = 0; // 0 -> T_2
                end
                10: begin
                    x = 1; y = 0; // 1
                end
                11: begin
                    x = 1; y = 1; // 0
                end
                12: begin
                    x = 0; y = 1; // 1 -> T_3
                end
                13: begin
                    x = 0; y = 1; // 1
                end
                14: begin
                    x = 1; y = 1; // 0 -> T_1
                end
                15: begin
                    x = 1; y = 0; // 1
                end
            endcase

            get_input_sequence = {x, y};
        end
    endfunction

    function automatic [4:0] get_types_sequence;
        input [2:0] i;

        reg [1:0] t;

        begin
            case(i[2:0])
                0: begin
                    t = 1;
                end
                1: begin
                    t = 3;
                end
                2: begin
                    t = 1;
                end
                3: begin
                    t = 2;
                end
                4: begin
                    t = 3;
                end
                5: begin
                    t = 1;
                end
                default: begin
                    t = 0;
                end
            endcase

            get_types_sequence = t;
        end
    endfunction
endmodule

// generatore del segnale di clock
module clock_generator(
    clock
);
    output clock;

    parameter HALF_PERIOD = 5;

    reg CLOCK;
    assign clock = CLOCK;

    initial CLOCK <= 0;
    always #HALF_PERIOD CLOCK <= ~CLOCK;

endmodule

verilog/2025-09-09/waveform_sintesi.vcd
$date
	Fri Dec  5 16:55:52 2025
$end
$version
	Icarus Verilog
$end
$timescale
	1s
$end
$scope module testbench $end
$var wire 2 ! t [1:0] $end
$var wire 1 " soc_y $end
$var wire 1 # soc_x $end
$var wire 1 $ dav_ $end
$var wire 1 % clock $end
$var reg 1 & eoc_x $end
$var reg 1 ' eoc_y $end
$var reg 1 ( error $end
$var reg 1 ) reset_ $end
$var reg 1 * rfd $end
$var reg 1 + x $end
$var reg 1 , y $end
$scope function get_input_sequence $end
$upscope $end
$scope function get_types_sequence $end
$upscope $end
$scope module clk $end
$var wire 1 % clock $end
$var parameter 32 - HALF_PERIOD $end
$var reg 1 . CLOCK $end
$upscope $end
$scope module dut $end
$var wire 1 % clock $end
$var wire 1 & eoc_x $end
$var wire 1 ' eoc_y $end
$var wire 1 ) reset_ $end
$var wire 1 * rfd $end
$var wire 1 + x $end
$var wire 1 , y $end
$var wire 2 / t [1:0] $end
$var wire 1 " soc_y $end
$var wire 1 # soc_x $end
$var wire 1 $ dav_ $end
$var wire 1 0 c2 $end
$var wire 1 1 c1 $end
$var wire 1 2 c0 $end
$var wire 1 3 b5 $end
$var wire 1 4 b4 $end
$var wire 1 5 b3 $end
$var wire 1 6 b2 $end
$var wire 1 7 b1 $end
$var wire 1 8 b0 $end
$scope module pc $end
$var wire 1 % clock $end
$var wire 1 ) reset_ $end
$var wire 1 0 c2 $end
$var wire 1 1 c1 $end
$var wire 1 2 c0 $end
$var wire 1 3 b5 $end
$var wire 1 4 b4 $end
$var wire 1 5 b3 $end
$var wire 1 6 b2 $end
$var wire 1 7 b1 $end
$var wire 1 8 b0 $end
$var parameter 32 9 S0 $end
$var parameter 32 : S1 $end
$var parameter 32 ; S2 $end
$var parameter 32 < S3 $end
$var parameter 32 = S4 $end
$var parameter 32 > S5 $end
$var reg 3 ? STAR [2:0] $end
$upscope $end
$scope module po $end
$var wire 1 8 b0 $end
$var wire 1 7 b1 $end
$var wire 1 6 b2 $end
$var wire 1 5 b3 $end
$var wire 1 4 b4 $end
$var wire 1 3 b5 $end
$var wire 1 2 c0 $end
$var wire 1 1 c1 $end
$var wire 1 0 c2 $end
$var wire 1 % clock $end
$var wire 1 $ dav_ $end
$var wire 1 & eoc_x $end
$var wire 1 ' eoc_y $end
$var wire 1 ) reset_ $end
$var wire 1 * rfd $end
$var wire 1 # soc_x $end
$var wire 1 " soc_y $end
$var wire 2 @ t [1:0] $end
$var wire 1 + x $end
$var wire 1 , y $end
$var wire 2 A match_type [1:0] $end
$var wire 1 B match $end
$var reg 4 C BUFFER [3:0] $end
$var reg 1 D DAV_ $end
$var reg 1 E SOC $end
$var reg 2 F T [1:0] $end
$scope module rc $end
$var wire 4 G buffer [3:0] $end
$var wire 1 H is_type_1 $end
$var wire 1 I is_type_2 $end
$var wire 1 J is_type_3 $end
$var wire 1 B match $end
$var wire 2 K match_type [1:0] $end
$upscope $end
$upscope $end
$upscope $end
$scope fork f $end
$scope begin consumer $end
$var reg 3 L i [2:0] $end
$var reg 2 M t_T [1:0] $end
$upscope $end
$scope begin producer_x $end
$var reg 5 N i [4:0] $end
$var reg 1 O t_x $end
$var reg 1 P t_y $end
$upscope $end
$scope begin producer_y $end
$var reg 5 Q i [4:0] $end
$var reg 1 R t_x $end
$var reg 1 S t_y $end
$upscope $end
$upscope $end
$upscope $end
$enddefinitions $end
$comment Show the parameter values. $end
$dumpall
b101 >
b100 =
b11 <
b10 ;
b1 :
b0 9
b101 -
$end
#0
$dumpvars
xS
xR
bx Q
xP
xO
bx N
bx M
bx L
bx K
xJ
xI
xH
bx G
bx F
xE
xD
bx C
xB
bx A
bx @
bx ?
x8
x7
x6
x5
x4
x3
x2
x1
x0
bx /
0.
x,
x+
1*
0)
0(
1'
1&
0%
x$
x#
x"
bx !
$end
#1
0"
0#
0E
b0 C
b0 G
1$
1D
b0 ?
12
10
#2
08
07
16
05
14
13
0H
0J
0I
#3
b0 A
b0 K
0B
#4
01
#5
1%
1.
0O
0P
b0 N
0R
0S
b0 Q
b1 M
b0 L
1)
#8
1"
1#
1E
#10
0%
0.
#15
1%
1.
#18
0&
#19
02
#20
0%
0.
#25
1%
1.
#28
b1 ?
0'
#29
18
#30
0%
0.
#35
1%
1.
#38
0"
0#
0E
#40
0%
0.
#45
1%
1.
#48
0+
#50
0%
0.
#55
1%
1.
#58
1&
0,
1O
b1 N
#60
0%
0.
#65
1%
1.
#70
0%
0.
#75
1%
1.
#78
1'
1R
b1 Q
#79
12
#80
0%
0.
#85
1%
1.
#88
b10 ?
#89
08
17
06
#90
0%
0.
#95
1%
1.
#98
b11 ?
#99
16
03
#100
0%
0.
#105
1%
1.
#108
b0 !
b0 /
b0 @
b0 F
b0 ?
#109
07
13
#110
0%
0.
#115
1%
1.
#118
1"
1#
1E
#120
0%
0.
#125
1%
1.
#128
0&
#129
02
#130
0%
0.
#135
1%
1.
#138
b1 ?
0'
#139
18
#140
0%
0.
#145
1%
1.
#148
0"
0#
0E
#150
0%
0.
#155
1%
1.
#158
1+
#160
0%
0.
#165
1%
1.
#168
1&
0O
1P
b10 N
#170
0%
0.
#175
1%
1.
#180
0%
0.
#185
1%
1.
#188
1'
0R
1S
b10 Q
#189
12
#190
0%
0.
#195
1%
1.
#198
b10 ?
#199
08
17
06
#200
0%
0.
#205
1%
1.
#208
b1 C
b1 G
b11 ?
#209
16
03
#210
0%
0.
#215
1%
1.
#218
b0 ?
#219
07
13
#220
0%
0.
#225
1%
1.
#228
1"
1#
1E
#230
0%
0.
#235
1%
1.
#238
0&
#239
02
#240
0%
0.
#245
1%
1.
#248
b1 ?
0'
#249
18
#250
0%
0.
#255
1%
1.
#258
0"
0#
0E
#260
0%
0.
#265
1%
1.
#268
0+
#270
0%
0.
#275
1%
1.
#278
1&
1,
1O
b11 N
#280
0%
0.
#285
1%
1.
#290
0%
0.
#295
1%
1.
#298
1'
1R
b11 Q
#299
12
#300
0%
0.
#305
1%
1.
#308
b10 ?
#309
08
17
06
#310
0%
0.
#315
1%
1.
#318
b11 ?
b11 C
b11 G
#319
16
03
#320
0%
0.
#325
1%
1.
#328
b0 ?
#329
07
13
#330
0%
0.
#335
1%
1.
#338
1"
1#
1E
#340
0%
0.
#345
1%
1.
#348
0&
#349
02
#350
0%
0.
#355
1%
1.
#358
b1 ?
0'
#359
18
#360
0%
0.
#365
1%
1.
#368
0"
0#
0E
#370
0%
0.
#375
1%
1.
#378
1+
#380
0%
0.
#385
1%
1.
#388
1&
0P
b100 N
#390
0%
0.
#395
1%
1.
#400
0%
0.
#405
1%
1.
#408
1'
0S
b100 Q
#409
12
#410
0%
0.
#415
1%
1.
#418
b10 ?
#419
08
17
06
#420
0%
0.
#425
1%
1.
#428
b110 C
b110 G
b11 ?
#429
16
03
1H
#430
0%
0.
1B
b1 A
b1 K
#431
11
#435
1%
1.
#438
b100 ?
b1 !
b1 /
b1 @
b1 F
#439
04
13
#440
0%
0.
#445
1%
1.
#448
0$
0D
#450
0%
0.
#455
1%
1.
#458
0*
#459
00
#460
0%
0.
#465
1%
1.
#468
b101 ?
#469
15
#470
0%
0.
#475
1%
1.
#478
1$
1D
#480
0%
0.
#485
1%
1.
#488
1*
b11 M
b1 L
#489
10
#490
0%
0.
#495
1%
1.
#498
b0 ?
#499
07
05
14
#500
0%
0.
#505
1%
1.
#508
1"
1#
1E
#510
0%
0.
#515
1%
1.
#518
0&
#519
02
#520
0%
0.
#525
1%
1.
#528
b1 ?
0'
#529
18
#530
0%
0.
#535
1%
1.
#538
0"
0#
0E
#540
0%
0.
#545
1%
1.
#550
0%
0.
#555
1%
1.
#558
1&
0,
0O
b101 N
#560
0%
0.
#565
1%
1.
#570
0%
0.
#575
1%
1.
#578
1'
0R
b101 Q
#579
12
#580
0%
0.
#585
1%
1.
#588
b10 ?
#589
08
17
06
#590
0%
0.
#595
1%
1.
#598
b11 ?
b1101 C
b1101 G
#599
16
03
0H
#600
0%
0.
0B
b0 A
b0 K
#601
01
#605
1%
1.
#608
b0 !
b0 /
b0 @
b0 F
b0 ?
#609
07
13
#610
0%
0.
#615
1%
1.
#618
1"
1#
1E
#620
0%
0.
#625
1%
1.
#628
0&
#629
02
#630
0%
0.
#635
1%
1.
#638
b1 ?
0'
#639
18
#640
0%
0.
#645
1%
1.
#648
0"
0#
0E
#650
0%
0.
#655
1%
1.
#658
0+
#660
0%
0.
#665
1%
1.
#668
1&
1P
b110 N
#670
0%
0.
#675
1%
1.
#680
0%
0.
#685
1%
1.
#688
1'
1S
b110 Q
#689
12
#690
0%
0.
#695
1%
1.
#698
b10 ?
#699
08
17
06
#700
0%
0.
#705
1%
1.
#708
b1010 C
b1010 G
b11 ?
#709
16
03
#710
0%
0.
#715
1%
1.
#718
b0 ?
#719
07
13
#720
0%
0.
#725
1%
1.
#728
1"
1#
1E
#730
0%
0.
#735
1%
1.
#738
0&
#739
02
#740
0%
0.
#745
1%
1.
#748
b1 ?
0'
#749
18
#750
0%
0.
#755
1%
1.
#758
0"
0#
0E
#760
0%
0.
#765
1%
1.
#770
0%
0.
#775
1%
1.
#778
1&
1,
1O
0P
b111 N
#780
0%
0.
#785
1%
1.
#790
0%
0.
#795
1%
1.
#798
1'
1R
0S
b111 Q
#799
12
#800
0%
0.
#805
1%
1.
#808
b10 ?
#809
08
17
06
#810
0%
0.
#815
1%
1.
#818
b11 ?
b101 C
b101 G
#819
16
03
1J
#820
0%
0.
b11 A
b11 K
1B
#821
11
#825
1%
1.
#828
b11 !
b11 /
b11 @
b11 F
b100 ?
#829
04
13
#830
0%
0.
#835
1%
1.
#838
0$
0D
#840
0%
0.
#845
1%
1.
#848
0*
#849
00
#850
0%
0.
#855
1%
1.
#858
b101 ?
#859
15
#860
0%
0.
#865
1%
1.
#868
1$
1D
#870
0%
0.
#875
1%
1.
#878
1*
b1 M
b10 L
#879
10
#880
0%
0.
#885
1%
1.
#888
b0 ?
#889
07
05
14
#890
0%
0.
#895
1%
1.
#898
1"
1#
1E
#900
0%
0.
#905
1%
1.
#908
0&
#909
02
#910
0%
0.
#915
1%
1.
#918
b1 ?
0'
#919
18
#920
0%
0.
#925
1%
1.
#928
0"
0#
0E
#930
0%
0.
#935
1%
1.
#938
1+
#940
0%
0.
#945
1%
1.
#948
1&
0,
1P
b1000 N
#950
0%
0.
#955
1%
1.
#960
0%
0.
#965
1%
1.
#968
1'
1S
b1000 Q
#969
12
#970
0%
0.
#975
1%
1.
#978
b10 ?
#979
08
17
06
#980
0%
0.
#985
1%
1.
#988
b1011 C
b1011 G
b11 ?
#989
16
03
0J
#990
0%
0.
b0 A
b0 K
0B
#991
01
#995
1%
1.
#998
b0 ?
b0 !
b0 /
b0 @
b0 F
#999
07
13
#1000
0%
0.
#1005
1%
1.
#1008
1"
1#
1E
#1010
0%
0.
#1015
1%
1.
#1018
0&
#1019
02
#1020
0%
0.
#1025
1%
1.
#1028
b1 ?
0'
#1029
18
#1030
0%
0.
#1035
1%
1.
#1038
0"
0#
0E
#1040
0%
0.
#1045
1%
1.
#1050
0%
0.
#1055
1%
1.
#1058
1&
1,
0O
0P
b1001 N
#1060
0%
0.
#1065
1%
1.
#1070
0%
0.
#1075
1%
1.
#1078
1'
0R
0S
b1001 Q
#1079
12
#1080
0%
0.
#1085
1%
1.
#1088
b10 ?
#1089
08
17
06
#1090
0%
0.
#1095
1%
1.
#1098
b11 ?
b110 C
b110 G
#1099
16
03
1H
#1100
0%
0.
1B
b1 A
b1 K
#1101
11
#1105
1%
1.
#1108
b1 !
b1 /
b1 @
b1 F
b100 ?
#1109
04
13
#1110
0%
0.
#1115
1%
1.
#1118
0$
0D
#1120
0%
0.
#1125
1%
1.
#1128
0*
#1129
00
#1130
0%
0.
#1135
1%
1.
#1138
b101 ?
#1139
15
#1140
0%
0.
#1145
1%
1.
#1148
1$
1D
#1150
0%
0.
#1155
1%
1.
#1158
1*
b10 M
b11 L
#1159
10
#1160
0%
0.
#1165
1%
1.
#1168
b0 ?
#1169
07
05
14
#1170
0%
0.
#1175
1%
1.
#1178
1"
1#
1E
#1180
0%
0.
#1185
1%
1.
#1188
0&
#1189
02
#1190
0%
0.
#1195
1%
1.
#1198
b1 ?
0'
#1199
18
#1200
0%
0.
#1205
1%
1.
#1208
0"
0#
0E
#1210
0%
0.
#1215
1%
1.
#1218
0+
#1220
0%
0.
#1225
1%
1.
#1228
1&
0,
1O
b1010 N
#1230
0%
0.
#1235
1%
1.
#1240
0%
0.
#1245
1%
1.
#1248
1'
1R
b1010 Q
#1249
12
#1250
0%
0.
#1255
1%
1.
#1258
b10 ?
#1259
08
17
06
#1260
0%
0.
#1265
1%
1.
#1268
b1100 C
b1100 G
b11 ?
#1269
16
03
1I
0H
#1270
0%
0.
b10 A
b10 K
#1275
1%
1.
#1278
b100 ?
b10 !
b10 /
b10 @
b10 F
#1279
04
13
#1280
0%
0.
#1285
1%
1.
#1288
0$
0D
#1290
0%
0.
#1295
1%
1.
#1298
0*
#1299
00
#1300
0%
0.
#1305
1%
1.
#1308
b101 ?
#1309
15
#1310
0%
0.
#1315
1%
1.
#1318
1$
1D
#1320
0%
0.
#1325
1%
1.
#1328
1*
b11 M
b100 L
#1329
10
#1330
0%
0.
#1335
1%
1.
#1338
b0 ?
#1339
07
05
14
#1340
0%
0.
#1345
1%
1.
#1348
1"
1#
1E
#1350
0%
0.
#1355
1%
1.
#1358
0&
#1359
02
#1360
0%
0.
#1365
1%
1.
#1368
b1 ?
0'
#1369
18
#1370
0%
0.
#1375
1%
1.
#1378
0"
0#
0E
#1380
0%
0.
#1385
1%
1.
#1388
1+
#1390
0%
0.
#1395
1%
1.
#1398
1&
1P
b1011 N
#1400
0%
0.
#1405
1%
1.
#1410
0%
0.
#1415
1%
1.
#1418
1'
1S
b1011 Q
#1419
12
#1420
0%
0.
#1425
1%
1.
#1428
b10 ?
#1429
08
17
06
#1430
0%
0.
#1435
1%
1.
#1438
b11 ?
b1001 C
b1001 G
#1439
16
03
0I
#1440
0%
0.
b0 A
b0 K
0B
#1441
01
#1445
1%
1.
#1448
b0 !
b0 /
b0 @
b0 F
b0 ?
#1449
07
13
#1450
0%
0.
#1455
1%
1.
#1458
1"
1#
1E
#1460
0%
0.
#1465
1%
1.
#1468
0&
#1469
02
#1470
0%
0.
#1475
1%
1.
#1478
b1 ?
0'
#1479
18
#1480
0%
0.
#1485
1%
1.
#1488
0"
0#
0E
#1490
0%
0.
#1495
1%
1.
#1500
0%
0.
#1505
1%
1.
#1508
1&
1,
0O
b1100 N
#1510
0%
0.
#1515
1%
1.
#1520
0%
0.
#1525
1%
1.
#1528
1'
0R
b1100 Q
#1529
12
#1530
0%
0.
#1535
1%
1.
#1538
b10 ?
#1539
08
17
06
#1540
0%
0.
#1545
1%
1.
#1548
b10 C
b10 G
b11 ?
#1549
16
03
#1550
0%
0.
#1555
1%
1.
#1558
b0 ?
#1559
07
13
#1560
0%
0.
#1565
1%
1.
#1568
1"
1#
1E
#1570
0%
0.
#1575
1%
1.
#1578
0&
#1579
02
#1580
0%
0.
#1585
1%
1.
#1588
b1 ?
0'
#1589
18
#1590
0%
0.
#1595
1%
1.
#1598
0"
0#
0E
#1600
0%
0.
#1605
1%
1.
#1608
0+
#1610
0%
0.
#1615
1%
1.
#1618
1&
b1101 N
#1620
0%
0.
#1625
1%
1.
#1630
0%
0.
#1635
1%
1.
#1638
1'
b1101 Q
#1639
12
#1640
0%
0.
#1645
1%
1.
#1648
b10 ?
#1649
08
17
06
#1650
0%
0.
#1655
1%
1.
#1658
b11 ?
b101 C
b101 G
#1659
16
03
1J
#1660
0%
0.
b11 A
b11 K
1B
#1661
11
#1665
1%
1.
#1668
b11 !
b11 /
b11 @
b11 F
b100 ?
#1669
04
13
#1670
0%
0.
#1675
1%
1.
#1678
0$
0D
#1680
0%
0.
#1685
1%
1.
#1688
0*
#1689
00
#1690
0%
0.
#1695
1%
1.
#1698
b101 ?
#1699
15
#1700
0%
0.
#1705
1%
1.
#1708
1$
1D
#1710
0%
0.
#1715
1%
1.
#1718
1*
b1 M
b101 L
#1719
10
#1720
0%
0.
#1725
1%
1.
#1728
b0 ?
#1729
07
05
14
#1730
0%
0.
#1735
1%
1.
#1738
1"
1#
1E
#1740
0%
0.
#1745
1%
1.
#1748
0&
#1749
02
#1750
0%
0.
#1755
1%
1.
#1758
b1 ?
0'
#1759
18
#1760
0%
0.
#1765
1%
1.
#1768
0"
0#
0E
#1770
0%
0.
#1775
1%
1.
#1780
0%
0.
#1785
1%
1.
#1788
1&
1O
b1110 N
#1790
0%
0.
#1795
1%
1.
#1800
0%
0.
#1805
1%
1.
#1808
1'
1R
b1110 Q
#1809
12
#1810
0%
0.
#1815
1%
1.
#1818
b10 ?
#1819
08
17
06
#1820
0%
0.
#1825
1%
1.
#1828
b1011 C
b1011 G
b11 ?
#1829
16
03
0J
#1830
0%
0.
b0 A
b0 K
0B
#1831
01
#1835
1%
1.
#1838
b0 ?
b0 !
b0 /
b0 @
b0 F
#1839
07
13
#1840
0%
0.
#1845
1%
1.
#1848
1"
1#
1E
#1850
0%
0.
#1855
1%
1.
#1858
0&
#1859
02
#1860
0%
0.
#1865
1%
1.
#1868
b1 ?
0'
#1869
18
#1870
0%
0.
#1875
1%
1.
#1878
0"
0#
0E
#1880
0%
0.
#1885
1%
1.
#1888
1+
#1890
0%
0.
#1895
1%
1.
#1898
1&
0P
b1111 N
#1900
0%
0.
#1905
1%
1.
#1910
0%
0.
#1915
1%
1.
#1918
1'
0S
b1111 Q
#1919
12
#1920
0%
0.
#1925
1%
1.
#1928
b10 ?
#1929
08
17
06
#1930
0%
0.
#1935
1%
1.
#1938
b11 ?
b110 C
b110 G
#1939
16
03
1H
#1940
0%
0.
1B
b1 A
b1 K
#1941
11
#1945
1%
1.
#1948
b1 !
b1 /
b1 @
b1 F
b100 ?
#1949
04
13
#1950
0%
0.
#1955
1%
1.
#1958
0$
0D
#1960
0%
0.
#1965
1%
1.
#1968
0*
#1969
00
#1970
0%
0.
#1975
1%
1.
#1978
b101 ?
#1979
15
#1980
0%
0.
#1985
1%
1.
#1988
1$
1D
#1990
0%
0.
#1995
1%
1.
#1998
1*
b110 L
#1999
10
#2000
0%
0.
#2005
1%
1.
#2008
b0 ?
#2009
07
05
14
#2010
0%
0.
#2015
1%
1.
#2018
1"
1#
1E
#2020
0%
0.
#2025
1%
1.
#2028
0&
#2029
02
#2030
0%
0.
#2035
1%
1.
#2038
b1 ?
0'
#2039
18
#2040
0%
0.
#2045
1%
1.
#2048
0"
0#
0E
#2050
0%
0.
#2055
1%
1.
#2060
0%
0.
#2065
1%
1.
#2068
1&
0,
b10000 N
#2070
0%
0.
#2075
1%
1.
#2080
0%
0.
#2085
1%
1.
#2088
1'
b10000 Q
